httpie_next.py
httpie_next-1.1.0.dist-info/LICENSE
httpie_next-1.1.0.dist-info/METADATA
httpie_next-1.1.0.dist-info/WHEEL
httpie_next-1.1.0.dist-info/entry_points.txt
httpie_next-1.1.0.dist-info/top_level.txt
httpie_next-1.1.0.dist-info/RECORD
