Metadata-Version: 2.1
Name: httpie-next
Version: 1.1.0
Summary: Use urllib3.future alongside HTTPie.
Home-page: https://github.com/Ousret/httpie-next
Author: Ahmed TAHRI
Author-email: ahmed.tahri@cloudnursery.dev
License: MIT
Classifier: Development Status :: 5 - Production/Stable
Classifier: Programming Language :: Python :: 3.7
Classifier: Programming Language :: Python :: 3.8
Classifier: Programming Language :: Python :: 3.9
Classifier: Programming Language :: Python :: 3.10
Classifier: Programming Language :: Python :: 3.11
Classifier: Programming Language :: Python :: 3.12
Classifier: Environment :: Plugins
Classifier: License :: OSI Approved :: MIT License
Classifier: Topic :: Internet :: WWW/HTTP
Classifier: Topic :: Utilities
License-File: LICENSE
Requires-Dist: httpie (>=3.0)
Requires-Dist: urllib3.future (>=2.0.931)
